scripts/__init__.py
scripts/python/__init__.py
scripts/python/simulate_range_noise.py
scripts/python/simulate_range_spots.py
scripts/python/simulate_range_spots_cluster.py
simfish/__init__.py
simfish/image_simulation.py
simfish/noise_simulation.py
simfish/pattern_simulation.py
simfish/spot_simulation.py
simfish/utils.py
simfish/tests/__init__.py
simfish/tests/test_image_simulation.py
simfish/tests/test_noise_simulation.py
simfish/tests/test_pattern_simulation.py
simfish/tests/test_spot_simulation.py
simfish/tests/test_utils.py
sim_fish-0.2.0.dist-info/LICENSE
sim_fish-0.2.0.dist-info/METADATA
sim_fish-0.2.0.dist-info/WHEEL
sim_fish-0.2.0.dist-info/top_level.txt
sim_fish-0.2.0.dist-info/RECORD
