Metadata-Version: 2.1
Name: sim-fish
Version: 0.2.0
Summary: Toolbox to simulate smFISH images.
Home-page: https://github.com/fish-quant/sim-fish
Author: Arthur Imbert
Author-email: arthur.imbert.pro@gmail.com
License: BSD 3-Clause License
Classifier: Development Status :: 5 - Production/Stable
Classifier: Intended Audience :: Science/Research
Classifier: Intended Audience :: Developers
Classifier: Topic :: Software Development
Classifier: Topic :: Scientific/Engineering
Classifier: Topic :: Scientific/Engineering :: Bio-Informatics
Classifier: Topic :: Scientific/Engineering :: Image Processing
Classifier: Operating System :: Unix
Classifier: Operating System :: MacOS
Classifier: Programming Language :: Python
Classifier: Programming Language :: Python :: 3.6
Classifier: Programming Language :: Python :: 3.7
Classifier: Programming Language :: Python :: 3.8
Classifier: Programming Language :: Python :: 3.9
Classifier: License :: OSI Approved :: BSD License
Requires-Python: >=3.6
License-File: LICENSE
Requires-Dist: big-fish (>=0.6.1)
Requires-Dist: joblib (>=0.13.2)
Requires-Dist: numpy (>=1.16.0)
Requires-Dist: scikit-image (>=0.14.2)
Requires-Dist: matplotlib (>=3.0.2)
Requires-Dist: pandas (>=0.24.0)
